radu_project/__init__.py
radu_project/radu.py
radu_first_project-0.1.1.dist-info/METADATA
radu_first_project-0.1.1.dist-info/WHEEL
radu_first_project-0.1.1.dist-info/top_level.txt
radu_first_project-0.1.1.dist-info/RECORD
