Metadata-Version: 2.1
Name: radu-first-project
Version: 0.1.1
Summary: Demo library
Home-page: UNKNOWN
Author: catalin
Author-email: raducatalin97@yahoo.com
License: UNKNOWN
Platform: UNKNOWN
